youtube_metrics/__init__.py
youtube_metrics/analyze.py
youtube_metrics/es.py
youtube_metrics/data/elasticsearch_template.json
youtube_metrics/lib/__init__.py
youtube_metrics/lib/convert.py
youtube_metrics/lib/net/__init__.py
youtube_metrics/lib/net/dns.py
youtube_metrics/lib/net/downloader.py
youtube_metrics/lib/net/geo.py
youtube_metrics/lib/net/local.py
youtube_metrics/lib/net/ping.py
youtube_metrics/lib/net/ping6.py
youtube_metrics/lib/net/quality_measurements.py
youtube_metrics/lib/net/data/GeoLite2-City/COPYRIGHT.txt
youtube_metrics/lib/net/data/GeoLite2-City/GeoLite2-City.mmdb
youtube_metrics/lib/net/data/GeoLite2-City/LICENSE.txt
youtube_metrics/lib/net/data/GeoLite2-City/README.txt
youtube_metrics/lib/net/youtube_dl/__init__.py
youtube_metrics/lib/net/youtube_dl/get_video_info.py
youtube_metrics-0.3.0.dist-info/LICENSE
youtube_metrics-0.3.0.dist-info/METADATA
youtube_metrics-0.3.0.dist-info/WHEEL
youtube_metrics-0.3.0.dist-info/entry_points.txt
youtube_metrics-0.3.0.dist-info/top_level.txt
youtube_metrics-0.3.0.dist-info/RECORD
