Metadata-Version: 2.1
Name: youtube-metrics
Version: 0.3.0
Summary: YouTube Metrics - Calculate Delivery Time of Videos
Home-page: https://gitlab.com/CryptidVulpes/youtube-metrics/
Author: CryptidVulpes
Author-email: "CryptidVulpes" <cvulpes@protonmail.com>
License: MIT License
Requires-Dist: geoip2
Requires-Dist: geopy
Requires-Dist: requests
Requires-Dist: dnspython
Requires-Dist: youtube-dl
Requires-Dist: humanize
